karmared_api/__init__.py
karmared_api/karma.py
karmared_api-0.0.3.dist-info/METADATA
karmared_api-0.0.3.dist-info/WHEEL
karmared_api-0.0.3.dist-info/top_level.txt
karmared_api-0.0.3.dist-info/RECORD
