Metadata-Version: 2.1
Name: karmared-api
Version: 0.0.3
Summary: UNKNOWN
Home-page: https://github.com/Karma-blockchain/karmared-api
Author: Nozdrin-Plotnitsky Nikolay
Author-email: nozdrin.plotnitsky@karma.red
License: MIT
Platform: UNKNOWN
Requires-Dist: aiohttp
Requires-Dist: graphql-core (>=3)
